LICENSE
README.md
setup.cfg
setup.py
icoextract/__init__.py
icoextract/version.py
icoextract.egg-info/PKG-INFO
icoextract.egg-info/SOURCES.txt
icoextract.egg-info/dependency_links.txt
icoextract.egg-info/entry_points.txt
icoextract.egg-info/requires.txt
icoextract.egg-info/top_level.txt
icoextract/scripts/__init__.py
icoextract/scripts/extract.py
icoextract/scripts/icolist.py
icoextract/scripts/thumbnailer.py